{
  "id": "10042",
  "key": "PROJ-1",
  "summary": "Implement login feature with OAuth 2.0",
  "description": "Users need to log in via Google OAuth 2.0. The login page should redirect to the OAuth consent screen and return a valid session token on success.",
  "status": "In Progress",
  "priority": "High",
  "assignee": "Alice Johnson",
  "reporter": "Bob Martinez",
  "labels": ["authentication", "oauth", "backend"],
  "created": "2026-05-01T09:00:00.000+0000",
  "updated": "2026-05-20T14:30:00.000+0000",
  "project": {
    "key": "PROJ",
    "name": "My SaaS Project"
  }
}
